README
setup.py
django_todoist.egg-info/PKG-INFO
django_todoist.egg-info/SOURCES.txt
django_todoist.egg-info/dependency_links.txt
django_todoist.egg-info/top_level.txt
todoist/__init__.py
todoist/admin.py
todoist/api.py
todoist/models.py
todoist/urls.py
todoist/views.py