Metadata-Version: 1.1
Name: django-todoist
Version: 0.1.0
Summary: Provides basic connectivity between Django and Todoist.
Home-page: http://bitbucket.org/neithere/django-todoist/
Author: Andy Mikhailenko
Author-email: andy@neithere.net
License: GNU Lesser General Public License (LGPL), Version 3
Download-URL: http://bitbucket.org/neithere/django-todoist/get/tip.zip
Keywords: django todoist sync
Platform: UNKNOWN
Classifier: Development Status :: 2 - Pre-Alpha
Classifier: Environment :: Web Environment
Classifier: Framework :: Django
Classifier: Intended Audience :: Developers
Classifier: License :: OSI Approved :: GNU Library or Lesser General Public License (LGPL)
Classifier: Programming Language :: Python
Classifier: Topic :: Software Development :: Libraries :: Python Modules
Requires: python (>= 2.4)
Requires: django (>= 1.0)
Requires: httplib2 (>= 0.5)
